README.md
setup.py
cops/__init__.py
cops.egg-info/PKG-INFO
cops.egg-info/SOURCES.txt
cops.egg-info/dependency_links.txt
cops.egg-info/entry_points.txt
cops.egg-info/requires.txt
cops.egg-info/top_level.txt
cops/aws/__init__.py
cops/aws/ec2.py
cops/aws/helper.py