Metadata-Version: 1.0
Name: cops
Version: 0.1.3
Summary: Cloud operation utilities
Home-page: https://github.com/rickhw/pipProject
Author: Rick Hwang
Author-email: rick_kyhwang@hotmail.com
License: MIT Licence
Keywords: pip,aws,ec2,provision,infra,iac,rickhwang
Platform: any
